README.md
setup.py
graphengine/__init__.py
graphengine.egg-info/PKG-INFO
graphengine.egg-info/SOURCES.txt
graphengine.egg-info/dependency_links.txt
graphengine.egg-info/not-zip-safe
graphengine.egg-info/top_level.txt