Metadata-Version: 1.0
Name: graphengine
Version: 0.0.1
Summary: Production of publication-quality graphs
Home-page: https://github.com/aslakjohansen/graphengine
Author: Aslak Johansen
Author-email: aslakj@gmail.com
License: GPLv3+
Platform: UNKNOWN
